<?xml version="1.0" encoding="utf-8"?>
<odoo>
    <template id="less" inherit_id="website.assets_frontend" active="True" priority="1">
        <xpath expr="." position="inside">
            <link href="/theme_yes/static/src/less/layout.less" rel="stylesheet" type="text/less"/>
            <link href="/theme_yes/static/src/less/snippets/s_banner_3.less" rel="stylesheet" type="text/less"/>
            <link href="/theme_yes/static/src/less/snippets/s_products_carousel.less" rel="stylesheet" type="text/less"/>
            <link href="/theme_yes/static/src/less/snippets/s_banner_parallax.less" rel="stylesheet" type="text/less"/>
        </xpath>
    </template>
</odoo>
