<?xml version="1.0" encoding="utf-8"?>
<odoo>

<template id="s_pricelist_boxed" inherit_id="website.s_pricelist_boxed">
    <xpath expr="//section" position="attributes">
        <attribute name="style"/>
        <attribute name="class" add="o_cc o_cc4" separator=" "/>
        <attribute name="data-oe-shape-data">{'shape':'web_editor/Bold/07_001','flip':[],'showOnMobile':false,'shapeAnimationSpeed':'0'}</attribute>
    </xpath>
    <xpath expr="//div[hasclass('o_container_small')]" position="before">
        <div class="o_we_shape o_web_editor_Bold_07_001"/>
    </xpath>
</template>

</odoo>
