<?xml version="1.0" encoding="utf-8"?>
<odoo>

<template id="s_key_benefits" inherit_id="website.s_key_benefits">
    <!-- Layout -->
    <xpath expr="//section" position="attributes">
        <attribute name="data-oe-shape-data"/>
    </xpath>
    <xpath expr="//div[hasclass('o_we_shape')]" position="replace"/>
    <xpath expr="//p[hasclass('lead')]" position="attributes">
        <attribute name="style">text-align: center;"</attribute>
    </xpath>
    <xpath expr="//h2" position="attributes">
        <attribute name="style" add="text-align: center;" separator=";"/>
        <attribute name="class">display-4-fs</attribute>
    </xpath>
    <xpath expr="(//span[hasclass('display-3-fs')])[2]" position="attributes">
        <attribute name="class" add="text-o-color-2" remove="text-o-color-1" separator=" "/>
    </xpath>
    <xpath expr="(//span[hasclass('display-3-fs')])[3]" position="attributes">
        <attribute name="class" add="text-o-color-5" remove="text-o-color-1" separator=" "/>
    </xpath>

</template>

</odoo>
